localzone/__init__.py
localzone/__version__.py
localzone/context.py
localzone/models.py
localzone/util.py
localzone-0.9.8.dist-info/LICENSE
localzone-0.9.8.dist-info/METADATA
localzone-0.9.8.dist-info/WHEEL
localzone-0.9.8.dist-info/top_level.txt
localzone-0.9.8.dist-info/RECORD
